__init__.py
asaas/__init__.py
asaas/api.py
asaas/apis/__init__.py
asaas/apis/accounts.py
asaas/apis/credit_cards.py
asaas/apis/customers.py
asaas/apis/payments.py
asaas/apis/subscriptions.py
asaas/apis/webhooks.py
asaas/dtos/__init__.py
asaas/dtos/account.py
asaas/dtos/credit_card.py
asaas/dtos/customer.py
asaas/dtos/payment.py
asaas/dtos/subscription.py
asaas/dtos/webhook.py
asaas_python_sdk-1.3.4.dist-info/licenses/LICENSE
asaas_python_sdk-1.3.4.dist-info/METADATA
asaas_python_sdk-1.3.4.dist-info/WHEEL
asaas_python_sdk-1.3.4.dist-info/top_level.txt
asaas_python_sdk-1.3.4.dist-info/RECORD
